<?xml version="1.0"?>
<ArrayOfParcel xmlns:xsi="http://www.w3.org/2001/XMLSchema-instance" xmlns:xsd="http://www.w3.org/2001/XMLSchema">
  <Parcel>
    <ID>1</ID>
    <SenderID>377561280</SenderID>
    <TargetID>703959091</TargetID>
    <Weight>heavy</Weight>
    <priority>normal</priority>
    <DroneId>0</DroneId>
    <Requested>2022-01-12T11:50:32.9946546+02:00</Requested>
    <Scheduled>2022-01-13T21:14:58.9954148+02:00</Scheduled>
    <PickedUp>2022-01-13T20:57:35.1572839+02:00</PickedUp>
    <Delivered>2022-01-13T20:57:41.9479276+02:00</Delivered>
    <Deleted>true</Deleted>
  </Parcel>
  <Parcel>
    <ID>2</ID>
    <SenderID>598505554</SenderID>
    <TargetID>930487635</TargetID>
    <Weight>normal</Weight>
    <priority>normal</priority>
    <DroneId>0</DroneId>
    <Requested>0001-01-01T00:00:00</Requested>
    <Scheduled>0001-01-01T00:00:00</Scheduled>
    <PickedUp>0001-01-01T00:00:00</PickedUp>
    <Delivered>0001-01-01T00:00:00</Delivered>
    <Deleted>true</Deleted>
  </Parcel>
  <Parcel>
    <ID>3</ID>
    <SenderID>861130331</SenderID>
    <TargetID>377561280</TargetID>
    <Weight>light</Weight>
    <priority>normal</priority>
    <DroneId>0</DroneId>
    <Requested>2022-01-12T11:50:33.0008137+02:00</Requested>
    <Scheduled>2022-01-14T12:26:50.6429429+02:00</Scheduled>
    <PickedUp>2022-01-14T12:26:56.3959958+02:00</PickedUp>
    <Delivered>0001-01-01T00:00:00</Delivered>
    <Deleted>false</Deleted>
  </Parcel>
  <Parcel>
    <ID>4</ID>
    <SenderID>598505554</SenderID>
    <TargetID>598505554</TargetID>
    <Weight>heavy</Weight>
    <priority>low</priority>
    <DroneId>0</DroneId>
    <Requested>2022-01-12T11:50:33.0008152+02:00</Requested>
    <Scheduled>2022-02-15T11:57:35.3022784+02:00</Scheduled>
    <PickedUp>2022-02-15T11:57:38.5536351+02:00</PickedUp>
    <Delivered>2022-02-15T11:58:10.3691622+02:00</Delivered>
    <Deleted>true</Deleted>
  </Parcel>
  <Parcel>
    <ID>5</ID>
    <SenderID>930487635</SenderID>
    <TargetID>876853018</TargetID>
    <Weight>light</Weight>
    <priority>low</priority>
    <DroneId>0</DroneId>
    <Requested>2022-01-12T11:50:33.0008162+02:00</Requested>
    <Scheduled>2022-02-19T22:20:21.8032386+02:00</Scheduled>
    <PickedUp>2022-02-19T22:20:25.2884049+02:00</PickedUp>
    <Delivered>2022-02-19T22:20:26.938908+02:00</Delivered>
    <Deleted>false</Deleted>
  </Parcel>
  <Parcel>
    <ID>6</ID>
    <SenderID>684351256</SenderID>
    <TargetID>180587831</TargetID>
    <Weight>normal</Weight>
    <priority>normal</priority>
    <DroneId>0</DroneId>
    <Requested>2022-01-12T11:50:33.0008182+02:00</Requested>
    <Scheduled>2022-01-14T09:38:01.5949642+02:00</Scheduled>
    <PickedUp>2022-01-14T09:38:30.2523456+02:00</PickedUp>
    <Delivered>2022-01-14T09:38:33.6171882+02:00</Delivered>
    <Deleted>false</Deleted>
  </Parcel>
  <Parcel>
    <ID>7</ID>
    <SenderID>421329093</SenderID>
    <TargetID>421329093</TargetID>
    <Weight>light</Weight>
    <priority>normal</priority>
    <DroneId>0</DroneId>
    <Requested>0001-01-01T00:00:00</Requested>
    <Scheduled>2022-02-20T09:16:48.9837288+02:00</Scheduled>
    <PickedUp>2022-02-20T09:16:55.4395872+02:00</PickedUp>
    <Delivered>2022-02-20T09:16:55.5663239+02:00</Delivered>
    <Deleted>false</Deleted>
  </Parcel>
  <Parcel>
    <ID>8</ID>
    <SenderID>377561280</SenderID>
    <TargetID>876853018</TargetID>
    <Weight>normal</Weight>
    <priority>hight</priority>
    <DroneId>0</DroneId>
    <Requested>0001-01-01T00:00:00</Requested>
    <Scheduled>0001-01-01T00:00:00</Scheduled>
    <PickedUp>0001-01-01T00:00:00</PickedUp>
    <Delivered>0001-01-01T00:00:00</Delivered>
    <Deleted>true</Deleted>
  </Parcel>
  <Parcel>
    <ID>9</ID>
    <SenderID>825061647</SenderID>
    <TargetID>861130331</TargetID>
    <Weight>light</Weight>
    <priority>low</priority>
    <DroneId>0</DroneId>
    <Requested>2022-01-12T11:50:33.0008208+02:00</Requested>
    <Scheduled>2022-02-18T16:14:32.8559846+02:00</Scheduled>
    <PickedUp>2022-02-18T16:14:37.53747+02:00</PickedUp>
    <Delivered>2022-02-18T16:14:49.0175712+02:00</Delivered>
    <Deleted>false</Deleted>
  </Parcel>
  <Parcel>
    <ID>10</ID>
    <SenderID>180587831</SenderID>
    <TargetID>684351256</TargetID>
    <Weight>normal</Weight>
    <priority>hight</priority>
    <DroneId>0</DroneId>
    <Requested>0001-01-01T00:00:00</Requested>
    <Scheduled>2022-02-20T09:16:24.3340071+02:00</Scheduled>
    <PickedUp>2022-02-20T09:16:38.8972319+02:00</PickedUp>
    <Delivered>2022-02-20T09:16:47.975967+02:00</Delivered>
    <Deleted>false</Deleted>
  </Parcel>
  <Parcel>
    <ID>100000</ID>
    <SenderID>598505554</SenderID>
    <TargetID>180587831</TargetID>
    <Weight>light</Weight>
    <priority>low</priority>
    <DroneId>0</DroneId>
    <Requested>2022-01-14T12:16:33.3991226+02:00</Requested>
    <Scheduled>2022-02-19T23:08:07.1408263+02:00</Scheduled>
    <PickedUp>2022-02-19T23:08:11.852303+02:00</PickedUp>
    <Delivered>2022-02-19T23:08:20.317482+02:00</Delivered>
    <Deleted>true</Deleted>
  </Parcel>
  <Parcel>
    <ID>100001</ID>
    <SenderID>598505554</SenderID>
    <TargetID>684351256</TargetID>
    <Weight>normal</Weight>
    <priority>normal</priority>
    <DroneId>0</DroneId>
    <Requested>2022-01-14T15:41:33.5166506+02:00</Requested>
    <Scheduled>2022-02-15T11:57:19.9177692+02:00</Scheduled>
    <PickedUp>2022-02-15T11:57:28.0977276+02:00</PickedUp>
    <Delivered>2022-02-15T11:57:31.6003213+02:00</Delivered>
    <Deleted>true</Deleted>
  </Parcel>
  <Parcel>
    <ID>100002</ID>
    <SenderID>421329093</SenderID>
    <TargetID>377561280</TargetID>
    <Weight>normal</Weight>
    <priority>low</priority>
    <DroneId>0</DroneId>
    <Requested>2022-01-17T11:40:33.7779574+02:00</Requested>
    <Scheduled>2022-02-15T11:58:54.4772443+02:00</Scheduled>
    <PickedUp>0001-01-01T00:00:00</PickedUp>
    <Delivered>0001-01-01T00:00:00</Delivered>
    <Deleted>false</Deleted>
  </Parcel>
  <Parcel>
    <ID>100003</ID>
    <SenderID>212829865</SenderID>
    <TargetID>377561280</TargetID>
    <Weight>light</Weight>
    <priority>low</priority>
    <DroneId>0</DroneId>
    <Requested>2022-02-15T11:43:48.1726453+02:00</Requested>
    <Scheduled>2022-02-19T23:07:17.6119149+02:00</Scheduled>
    <PickedUp>2022-02-20T00:49:39.8050295+02:00</PickedUp>
    <Delivered>2022-02-20T00:49:41.2646585+02:00</Delivered>
    <Deleted>false</Deleted>
  </Parcel>
  <Parcel>
    <ID>100004</ID>
    <SenderID>212829865</SenderID>
    <TargetID>930487635</TargetID>
    <Weight>light</Weight>
    <priority>low</priority>
    <DroneId>0</DroneId>
    <Requested>2022-02-15T11:55:23.2999698+02:00</Requested>
    <Scheduled>2022-02-19T23:08:43.115538+02:00</Scheduled>
    <PickedUp>2022-02-19T23:08:49.8598321+02:00</PickedUp>
    <Delivered>2022-02-19T23:09:13.8472089+02:00</Delivered>
    <Deleted>false</Deleted>
  </Parcel>
  <Parcel>
    <ID>100005</ID>
    <SenderID>212829865</SenderID>
    <TargetID>684351256</TargetID>
    <Weight>normal</Weight>
    <priority>low</priority>
    <DroneId>0</DroneId>
    <Requested>2022-02-15T12:36:46.0659825+02:00</Requested>
    <Scheduled>2022-02-19T23:09:15.1328318+02:00</Scheduled>
    <PickedUp>2022-02-19T23:09:40.2505736+02:00</PickedUp>
    <Delivered>2022-02-19T23:09:59.4392986+02:00</Delivered>
    <Deleted>false</Deleted>
  </Parcel>
  <Parcel>
    <ID>100006</ID>
    <SenderID>33574773</SenderID>
    <TargetID>212829865</TargetID>
    <Weight>light</Weight>
    <priority>hight</priority>
    <DroneId>0</DroneId>
    <Requested>2022-02-15T12:39:00.8917151+02:00</Requested>
    <Scheduled>2022-02-19T23:06:58.5235927+02:00</Scheduled>
    <PickedUp>2022-02-19T23:07:01.9473703+02:00</PickedUp>
    <Delivered>2022-02-19T23:07:07.1775884+02:00</Delivered>
    <Deleted>false</Deleted>
  </Parcel>
  <Parcel>
    <ID>100007</ID>
    <SenderID>598505554</SenderID>
    <TargetID>180587831</TargetID>
    <Weight>light</Weight>
    <priority>normal</priority>
    <DroneId>0</DroneId>
    <Requested>2022-02-16T21:48:28.7709067+02:00</Requested>
    <Scheduled>2022-02-16T22:11:20.1396018+02:00</Scheduled>
    <PickedUp>2022-02-16T22:11:24.0332037+02:00</PickedUp>
    <Delivered>2022-02-16T22:11:26.7784831+02:00</Delivered>
    <Deleted>true</Deleted>
  </Parcel>
  <Parcel>
    <ID>100008</ID>
    <SenderID>212829865</SenderID>
    <TargetID>180587831</TargetID>
    <Weight>normal</Weight>
    <priority>low</priority>
    <DroneId>0</DroneId>
    <Requested>2022-02-16T21:55:12.0954118+02:00</Requested>
    <Scheduled>2022-02-18T16:14:50.0402608+02:00</Scheduled>
    <PickedUp>2022-02-18T16:15:06.2570869+02:00</PickedUp>
    <Delivered>2022-02-18T16:15:21.9531556+02:00</Delivered>
    <Deleted>false</Deleted>
  </Parcel>
  <Parcel>
    <ID>100009</ID>
    <SenderID>703959091</SenderID>
    <TargetID>180587831</TargetID>
    <Weight>light</Weight>
    <priority>low</priority>
    <DroneId>0</DroneId>
    <Requested>2022-02-19T20:53:21.7335247+02:00</Requested>
    <Scheduled>2022-02-19T20:55:56.7598298+02:00</Scheduled>
    <PickedUp>2022-02-19T20:57:23.2801353+02:00</PickedUp>
    <Delivered>2022-02-19T21:00:36.6950223+02:00</Delivered>
    <Deleted>false</Deleted>
  </Parcel>
  <Parcel>
    <ID>100010</ID>
    <SenderID>861130331</SenderID>
    <TargetID>684351256</TargetID>
    <Weight>light</Weight>
    <priority>low</priority>
    <DroneId>0</DroneId>
    <Requested>2022-02-19T20:53:36.6820015+02:00</Requested>
    <Scheduled>2022-02-19T21:02:32.3640468+02:00</Scheduled>
    <PickedUp>2022-02-19T21:02:52.4227465+02:00</PickedUp>
    <Delivered>0001-01-01T00:00:00</Delivered>
    <Deleted>false</Deleted>
  </Parcel>
  <Parcel>
    <ID>100011</ID>
    <SenderID>825061647</SenderID>
    <TargetID>684351256</TargetID>
    <Weight>light</Weight>
    <priority>low</priority>
    <DroneId>0</DroneId>
    <Requested>2022-02-20T08:13:26.8073541+02:00</Requested>
    <Scheduled>2022-02-20T08:14:09.5947849+02:00</Scheduled>
    <PickedUp>2022-02-20T08:16:02.2045672+02:00</PickedUp>
    <Delivered>2022-02-20T08:16:07.1550735+02:00</Delivered>
    <Deleted>false</Deleted>
  </Parcel>
  <Parcel>
    <ID>100012</ID>
    <SenderID>180587831</SenderID>
    <TargetID>930487635</TargetID>
    <Weight>normal</Weight>
    <priority>low</priority>
    <DroneId>0</DroneId>
    <Requested>2022-02-20T08:13:44.4953474+02:00</Requested>
    <Scheduled>2022-02-20T08:22:13.0503755+02:00</Scheduled>
    <PickedUp>2022-02-20T08:22:18.0735686+02:00</PickedUp>
    <Delivered>2022-02-20T08:22:21.0797962+02:00</Delivered>
    <Deleted>false</Deleted>
  </Parcel>
  <Parcel>
    <ID>100013</ID>
    <SenderID>876853018</SenderID>
    <TargetID>684351256</TargetID>
    <Weight>light</Weight>
    <priority>low</priority>
    <DroneId>0</DroneId>
    <Requested>2022-02-20T08:30:30.1754366+02:00</Requested>
    <Scheduled>2022-02-20T08:32:27.4997133+02:00</Scheduled>
    <PickedUp>2022-02-20T08:33:05.8776575+02:00</PickedUp>
    <Delivered>2022-02-20T08:33:15.2339106+02:00</Delivered>
    <Deleted>false</Deleted>
  </Parcel>
  <Parcel>
    <ID>100014</ID>
    <SenderID>684351256</SenderID>
    <TargetID>861130331</TargetID>
    <Weight>light</Weight>
    <priority>normal</priority>
    <DroneId>0</DroneId>
    <Requested>2022-02-20T08:30:45.0324311+02:00</Requested>
    <Scheduled>2022-02-20T08:31:10.7100535+02:00</Scheduled>
    <PickedUp>2022-02-20T08:31:20.7762394+02:00</PickedUp>
    <Delivered>2022-02-20T08:31:34.4535585+02:00</Delivered>
    <Deleted>false</Deleted>
  </Parcel>
  <Parcel>
    <ID>100015</ID>
    <SenderID>684351256</SenderID>
    <TargetID>1111</TargetID>
    <Weight>light</Weight>
    <priority>low</priority>
    <DroneId>1</DroneId>
    <Requested>2022-02-20T08:31:00.4582606+02:00</Requested>
    <Scheduled>2022-02-20T08:31:35.4612319+02:00</Scheduled>
    <PickedUp>2022-02-20T08:31:50.1892986+02:00</PickedUp>
    <Delivered>0001-01-01T00:00:00</Delivered>
    <Deleted>false</Deleted>
  </Parcel>
  <Parcel>
    <ID>100016</ID>
    <SenderID>684351256</SenderID>
    <TargetID>861130331</TargetID>
    <Weight>light</Weight>
    <priority>low</priority>
    <DroneId>0</DroneId>
    <Requested>2022-02-20T08:38:26.735558+02:00</Requested>
    <Scheduled>2022-02-20T08:39:10.868135+02:00</Scheduled>
    <PickedUp>2022-02-20T08:39:20.9579387+02:00</PickedUp>
    <Delivered>2022-02-20T08:39:34.633523+02:00</Delivered>
    <Deleted>false</Deleted>
  </Parcel>
  <Parcel>
    <ID>100017</ID>
    <SenderID>377561280</SenderID>
    <TargetID>180587831</TargetID>
    <Weight>light</Weight>
    <priority>low</priority>
    <DroneId>0</DroneId>
    <Requested>2022-02-20T08:38:41.4355731+02:00</Requested>
    <Scheduled>2022-02-20T08:38:52.4838454+02:00</Scheduled>
    <PickedUp>2022-02-20T08:39:01.4862328+02:00</PickedUp>
    <Delivered>2022-02-20T08:39:09.8621275+02:00</Delivered>
    <Deleted>false</Deleted>
  </Parcel>
  <Parcel>
    <ID>100018</ID>
    <SenderID>703959091</SenderID>
    <TargetID>684351256</TargetID>
    <Weight>light</Weight>
    <priority>low</priority>
    <DroneId>0</DroneId>
    <Requested>2022-02-20T08:44:33.9849311+02:00</Requested>
    <Scheduled>2022-02-20T08:44:42.780378+02:00</Scheduled>
    <PickedUp>2022-02-20T08:44:48.3580471+02:00</PickedUp>
    <Delivered>2022-02-20T08:44:56.1973388+02:00</Delivered>
    <Deleted>false</Deleted>
  </Parcel>
  <Parcel>
    <ID>100019</ID>
    <SenderID>598505554</SenderID>
    <TargetID>180587831</TargetID>
    <Weight>light</Weight>
    <priority>low</priority>
    <DroneId>0</DroneId>
    <Requested>2022-02-20T09:23:05.5774719+02:00</Requested>
    <Scheduled>2022-02-20T09:23:48.1687246+02:00</Scheduled>
    <PickedUp>2022-02-20T09:24:11.104179+02:00</PickedUp>
    <Delivered>2022-02-20T09:24:19.4309638+02:00</Delivered>
    <Deleted>false</Deleted>
  </Parcel>
  <Parcel>
    <ID>100020</ID>
    <SenderID>180587831</SenderID>
    <TargetID>684351256</TargetID>
    <Weight>light</Weight>
    <priority>low</priority>
    <DroneId>2</DroneId>
    <Requested>2022-02-20T09:38:48.6592042+02:00</Requested>
    <Scheduled>2022-02-20T09:39:14.5516827+02:00</Scheduled>
    <PickedUp>2022-02-20T09:39:48.7703849+02:00</PickedUp>
    <Delivered>0001-01-01T00:00:00</Delivered>
    <Deleted>false</Deleted>
  </Parcel>
  <Parcel>
    <ID>100021</ID>
    <SenderID>703959091</SenderID>
    <TargetID>684351256</TargetID>
    <Weight>light</Weight>
    <priority>low</priority>
    <DroneId>0</DroneId>
    <Requested>2022-02-20T09:44:18.7949587+02:00</Requested>
    <Scheduled>2022-02-20T09:44:28.5714874+02:00</Scheduled>
    <PickedUp>2022-02-20T09:44:35.4709931+02:00</PickedUp>
    <Delivered>2022-02-20T09:44:44.6829104+02:00</Delivered>
    <Deleted>false</Deleted>
  </Parcel>
</ArrayOfParcel>